house/__init__.py
house-0.1.10.dist-info/DESCRIPTION.rst
house-0.1.10.dist-info/METADATA
house-0.1.10.dist-info/RECORD
house-0.1.10.dist-info/WHEEL
house-0.1.10.dist-info/metadata.json
house-0.1.10.dist-info/top_level.txt
